aind_behavior_vr_foraging/__init__.py
aind_behavior_vr_foraging/cli.py
aind_behavior_vr_foraging/data_contract/__init__.py
aind_behavior_vr_foraging/data_contract/utils.py
aind_behavior_vr_foraging/data_contract/v0_4_0.py
aind_behavior_vr_foraging/data_contract/v0_5_0.py
aind_behavior_vr_foraging/data_contract/v0_6_0.py
aind_behavior_vr_foraging/data_mappers/__init__.py
aind_behavior_vr_foraging/data_mappers/_rig.py
aind_behavior_vr_foraging/data_mappers/_session.py
aind_behavior_vr_foraging/data_mappers/_utils.py
aind_behavior_vr_foraging/data_qc/__init__.py
aind_behavior_vr_foraging/data_qc/data_qc.py
aind_behavior_vr_foraging/launcher.py
aind_behavior_vr_foraging/regenerate.py
aind_behavior_vr_foraging/rig.py
aind_behavior_vr_foraging/task_logic.py
aind_behavior_vr_foraging-0.6.4.dist-info/WHEEL
aind_behavior_vr_foraging-0.6.4.dist-info/entry_points.txt
aind_behavior_vr_foraging-0.6.4.dist-info/METADATA
aind_behavior_vr_foraging-0.6.4.dist-info/RECORD
