Metadata-Version: 2.4
Name: aind-behavior-vr-foraging
Version: 0.6.4
Summary: A library that defines AIND data schema for the Aind Behavior VR Foraging experiment.
Author: Bruno Cruz
Author-email: Bruno Cruz <bruno.cruz@alleninstitute.org>
License-Expression: MIT
Classifier: Programming Language :: Python :: 3.11
Classifier: Operating System :: Microsoft :: Windows
Requires-Dist: aind-behavior-services>=0.12,<0.13
Requires-Dist: pydantic-settings
Requires-Dist: contraqctor>=0.5.3,<0.6.0 ; extra == 'data'
Requires-Dist: aind-clabe[aind-services]>=0.9.1 ; extra == 'launcher'
Requires-Dist: aind-data-schema>=2.2 ; extra == 'launcher'
Requires-Dist: aind-behavior-vr-foraging[data] ; extra == 'launcher'
Requires-Dist: aind-watchdog-service==0.1.6.dev8 ; extra == 'launcher'
Requires-Python: >=3.11
Project-URL: Changelog, https://github.com/AllenNeuralDynamics/Aind.Behavior.VrForaging/releases
Project-URL: Documentation, https://allenneuraldynamics.github.io/Aind.Behavior.VrForaging/
Project-URL: Issues, https://github.com/AllenNeuralDynamics/Aind.Behavior.VrForaging/issues
Project-URL: Repository, https://github.com/AllenNeuralDynamics/Aind.Behavior.VrForaging/
Provides-Extra: data
Provides-Extra: launcher
